ordeq_yaml/__init__.py
ordeq_yaml/_version.py
ordeq_yaml/py.typed
ordeq_yaml/yaml.py
ordeq_yaml-1.0.1.dist-info/licenses/LICENSE
ordeq_yaml-1.0.1.dist-info/METADATA
ordeq_yaml-1.0.1.dist-info/WHEEL
ordeq_yaml-1.0.1.dist-info/top_level.txt
ordeq_yaml-1.0.1.dist-info/RECORD
